sphinx_favicon/__init__.py
sphinx_favicon-1.0.1.dist-info/LICENSE
sphinx_favicon-1.0.1.dist-info/METADATA
sphinx_favicon-1.0.1.dist-info/WHEEL
sphinx_favicon-1.0.1.dist-info/top_level.txt
sphinx_favicon-1.0.1.dist-info/RECORD
